AUTHORS
ChangeLog
LICENSE
README.rst
requirements.txt
setup.cfg
setup.py
tox.ini
opentracing_pyzipkin/span.py
opentracing_pyzipkin/tracer.py
opentracing_pyzipkin.egg-info/PKG-INFO
opentracing_pyzipkin.egg-info/SOURCES.txt
opentracing_pyzipkin.egg-info/dependency_links.txt
opentracing_pyzipkin.egg-info/not-zip-safe
opentracing_pyzipkin.egg-info/pbr.json
opentracing_pyzipkin.egg-info/requires.txt
opentracing_pyzipkin.egg-info/top_level.txt
opentracing_pyzipkin/_opentracing/__init__.py
opentracing_pyzipkin/_opentracing/propagation.py
opentracing_pyzipkin/_opentracing/span.py
opentracing_pyzipkin/_opentracing/tracer.py
opentracing_pyzipkin/tests/__init__.py
opentracing_pyzipkin/tests/unit/__init__.py
opentracing_pyzipkin/tests/unit/test_tracer.py
opentracing_pyzipkin/transports/__init__.py
opentracing_pyzipkin/transports/http.py