Metadata-Version: 1.1
Name: opentracing-pyzipkin
Version: 0.0.1
Summary: Opentracing implementation for python + zipkin
Home-page: UNKNOWN
Author: Gregory Haynes <greg@greghaynes.net>
Author-email: greg@greghaynes.net
License: UNKNOWN
Platform: UNKNOWN
Classifier: Development Status :: 2 - Pre-Alpha
Classifier: Programming Language :: Python
Classifier: Programming Language :: Python :: 2
Classifier: Programming Language :: Python :: 2.7
Classifier: Programming Language :: Python :: 3
Classifier: Programming Language :: Python :: 3.5
